xicor/__init__.py
xicor/version.py
xicor/xicor.py
xicor/xicor_pandas.py
xicor/notebooks/profiling.ipynb
xicor-1.0.1.dist-info/LICENSE
xicor-1.0.1.dist-info/METADATA
xicor-1.0.1.dist-info/WHEEL
xicor-1.0.1.dist-info/top_level.txt
xicor-1.0.1.dist-info/RECORD
