Metadata-Version: 2.1
Name: xicor
Version: 1.0.1
Summary: xi correlation for tied data
Home-page: https://github.com/czbiohub/xicor/
Author: Phoenix Logan
Author-email: phoenix.logan@czbiohub.org
Maintainer: Pranathi Vemuri
Maintainer-email: pranathi93.vemuri@gmail.com
License: MIT
Platform: UNKNOWN
Classifier: Programming Language :: Python :: 3
Classifier: License :: OSI Approved :: MIT License
Classifier: Operating System :: OS Independent
Requires-Dist: scipy (>=1.4.1)
Requires-Dist: pytest
Requires-Dist: pytest-cov
Requires-Dist: numpy
Requires-Dist: black
Provides-Extra: test
Requires-Dist: pytest ; extra == 'test'
Requires-Dist: coverage ; extra == 'test'
Requires-Dist: pytest-cov ; extra == 'test'
